[
null,
{"id":1,"animationId":0,"consumable":true,"damage":{"critical":false,"elementId":0,"formula":"b.mmp/4","type":4,"variance":0},"description":"Restores 25% of the drinker's maximum mana.\nAlso heals most negative status effects.","effects":[{"code":22,"dataId":4,"value1":1,"value2":0},{"code":22,"dataId":5,"value1":1,"value2":0},{"code":22,"dataId":13,"value1":1,"value2":0},{"code":22,"dataId":11,"value1":1,"value2":0}],"hitType":0,"iconIndex":64,"itypeId":1,"name":"Can of Soda","note":"","occasion":0,"price":1,"repeats":1,"scope":7,"speed":0,"successRate":100,"tpGain":0},
{"id":2,"animationId":0,"consumable":false,"damage":{"critical":false,"elementId":0,"formula":"0","type":0,"variance":20},"description":"Notes about magic. Can be used to study and master \nnew runes and secrets.","effects":[],"hitType":0,"iconIndex":108,"itypeId":2,"name":"Study Points","note":"","occasion":3,"price":0,"repeats":1,"scope":0,"speed":0,"successRate":100,"tpGain":0},
{"id":3,"animationId":0,"consumable":true,"damage":{"critical":false,"elementId":0,"formula":"b.mmp","type":4,"variance":0},"description":"Restores the drinker to maximum mana.\nAlso heals most negative status effects.","effects":[{"code":22,"dataId":4,"value1":1,"value2":0},{"code":22,"dataId":5,"value1":1,"value2":0},{"code":22,"dataId":13,"value1":1,"value2":0},{"code":22,"dataId":11,"value1":1,"value2":0}],"hitType":0,"iconIndex":65,"itypeId":1,"name":"Coffee","note":"","occasion":0,"price":1,"repeats":1,"scope":7,"speed":0,"successRate":100,"tpGain":0},
{"id":4,"animationId":0,"consumable":true,"damage":{"critical":false,"elementId":0,"formula":"b.mhp/4","type":3,"variance":0},"description":"Restore 25% of the eater's maximum health.\nAlso heals most negative status effects.","effects":[{"code":22,"dataId":4,"value1":1,"value2":0},{"code":22,"dataId":5,"value1":1,"value2":0},{"code":22,"dataId":13,"value1":1,"value2":0},{"code":22,"dataId":11,"value1":1,"value2":0}],"hitType":0,"iconIndex":66,"itypeId":1,"name":"Candy Bar","note":"","occasion":0,"price":1,"repeats":1,"scope":7,"speed":0,"successRate":100,"tpGain":0},
{"id":5,"animationId":0,"consumable":true,"damage":{"critical":false,"elementId":0,"formula":"b.mhp/4","type":0,"variance":0},"description":"Restore 50% of the drinker's maximum mana and \ngrants them mana regeneration for a short time.","effects":[{"code":21,"dataId":16,"value1":1,"value2":0}],"hitType":0,"iconIndex":67,"itypeId":1,"name":"Bottled Drink","note":"","occasion":0,"price":1,"repeats":1,"scope":7,"speed":0,"successRate":100,"tpGain":0},
{"id":6,"animationId":0,"consumable":false,"damage":{"critical":false,"elementId":0,"formula":"0","type":0,"variance":20},"description":"Notes regarding secret and restricted magical arts.","effects":[],"hitType":0,"iconIndex":88,"itypeId":2,"name":"Dark Study Points","note":"","occasion":3,"price":0,"repeats":1,"scope":0,"speed":0,"successRate":100,"tpGain":0},
{"id":7,"animationId":0,"consumable":false,"damage":{"critical":false,"elementId":0,"formula":"0","type":0,"variance":20},"description":"Your smartphone.","effects":[],"hitType":0,"iconIndex":56,"itypeId":2,"name":"Phone","note":"","occasion":2,"price":0,"repeats":1,"scope":0,"speed":0,"successRate":100,"tpGain":0},
{"id":8,"animationId":0,"consumable":true,"damage":{"critical":false,"elementId":0,"formula":"10","type":4,"variance":0},"description":"Absorb this crystal to regain 10 mana or\nsell the crystal at the shop for $10.","effects":[],"hitType":0,"iconIndex":100,"itypeId":1,"name":"Mana Crystal","note":"","occasion":0,"price":10,"repeats":1,"scope":7,"speed":0,"successRate":100,"tpGain":0},
{"id":9,"animationId":0,"consumable":true,"damage":{"critical":false,"elementId":0,"formula":"0","type":0,"variance":20},"description":"","effects":[],"hitType":0,"iconIndex":0,"itypeId":1,"name":"","note":"","occasion":0,"price":0,"repeats":1,"scope":7,"speed":0,"successRate":100,"tpGain":0},
{"id":10,"animationId":0,"consumable":true,"damage":{"critical":false,"elementId":0,"formula":"0","type":0,"variance":20},"description":"","effects":[],"hitType":0,"iconIndex":0,"itypeId":1,"name":"","note":"","occasion":0,"price":0,"repeats":1,"scope":7,"speed":0,"successRate":100,"tpGain":0},
{"id":11,"animationId":0,"consumable":true,"damage":{"critical":false,"elementId":0,"formula":"0","type":0,"variance":20},"description":"","effects":[],"hitType":0,"iconIndex":0,"itypeId":1,"name":"","note":"","occasion":0,"price":0,"repeats":1,"scope":7,"speed":0,"successRate":100,"tpGain":0},
{"id":12,"animationId":0,"consumable":true,"damage":{"critical":false,"elementId":0,"formula":"0","type":0,"variance":20},"description":"","effects":[],"hitType":0,"iconIndex":0,"itypeId":1,"name":"","note":"","occasion":0,"price":0,"repeats":1,"scope":7,"speed":0,"successRate":100,"tpGain":0},
{"id":13,"animationId":0,"consumable":true,"damage":{"critical":false,"elementId":0,"formula":"0","type":0,"variance":20},"description":"","effects":[],"hitType":0,"iconIndex":0,"itypeId":1,"name":"","note":"","occasion":0,"price":0,"repeats":1,"scope":7,"speed":0,"successRate":100,"tpGain":0},
{"id":14,"animationId":0,"consumable":true,"damage":{"critical":false,"elementId":0,"formula":"0","type":0,"variance":20},"description":"","effects":[],"hitType":0,"iconIndex":0,"itypeId":1,"name":"","note":"","occasion":0,"price":0,"repeats":1,"scope":7,"speed":0,"successRate":100,"tpGain":0},
{"id":15,"animationId":0,"consumable":true,"damage":{"critical":false,"elementId":0,"formula":"0","type":0,"variance":20},"description":"","effects":[],"hitType":0,"iconIndex":0,"itypeId":1,"name":"","note":"","occasion":0,"price":0,"repeats":1,"scope":7,"speed":0,"successRate":100,"tpGain":0},
{"id":16,"animationId":0,"consumable":true,"damage":{"critical":false,"elementId":0,"formula":"0","type":0,"variance":20},"description":"","effects":[],"hitType":0,"iconIndex":0,"itypeId":1,"name":"","note":"","occasion":0,"price":0,"repeats":1,"scope":7,"speed":0,"successRate":100,"tpGain":0},
{"id":17,"animationId":0,"consumable":true,"damage":{"critical":false,"elementId":0,"formula":"0","type":0,"variance":20},"description":"","effects":[],"hitType":0,"iconIndex":0,"itypeId":1,"name":"","note":"","occasion":0,"price":0,"repeats":1,"scope":7,"speed":0,"successRate":100,"tpGain":0},
{"id":18,"animationId":0,"consumable":true,"damage":{"critical":false,"elementId":0,"formula":"0","type":0,"variance":20},"description":"","effects":[],"hitType":0,"iconIndex":0,"itypeId":1,"name":"","note":"","occasion":0,"price":0,"repeats":1,"scope":7,"speed":0,"successRate":100,"tpGain":0}
]